cerebras/sdk/__init__.py
cerebras/sdk/client/__init__.py
cerebras/sdk/client/_version.py
cerebras/sdk/client/debug_util.py
cerebras/sdk/client/sdk_appliance_client.py
cerebras/sdk/client/sdk_appliance_utils.py
cerebras/sdk/client/sdk_utils.py
cerebras_sdk-2.7.1.dist-info/LICENSE
cerebras_sdk-2.7.1.dist-info/METADATA
cerebras_sdk-2.7.1.dist-info/WHEEL
cerebras_sdk-2.7.1.dist-info/top_level.txt
cerebras_sdk-2.7.1.dist-info/RECORD
