Metadata-Version: 2.1
Name: cerebras-sdk
Version: 2.7.1
Summary: Cerebras Wafer Scale Cluster SDK
Home-page: https://cerebras.net/
Author: Cerebras Systems
Author-email: support@cerebras.net
Classifier: Development Status :: 5 - Production/Stable
Classifier: Intended Audience :: Developers
Classifier: Intended Audience :: Science/Research
Classifier: Topic :: Scientific/Engineering :: Artificial Intelligence
Classifier: Topic :: Software Development
Classifier: Topic :: Software Development :: Libraries
Classifier: Topic :: System :: Hardware
Classifier: License :: OSI Approved :: BSD License
Classifier: Programming Language :: Python :: 3
License-File: LICENSE
Requires-Dist: cerebras-appliance (==2.7.1)
